Castl/__init__.py
Castl/castl.py
Castl/preprocess.py
Castl/utils.py
Castl/version.py
STCastl-0.1.1.dist-info/LICENSE
STCastl-0.1.1.dist-info/METADATA
STCastl-0.1.1.dist-info/WHEEL
STCastl-0.1.1.dist-info/top_level.txt
STCastl-0.1.1.dist-info/RECORD
