Metadata-Version: 2.1
Name: STCastl
Version: 0.1.1
Summary: A Consensus Framework for Robust Identification of Spatially Variable Genes in Spatial Transcriptomics
Home-page: https://github.com/TheY11/Castl
Author: Yiyi Yu
Author-email: yiyiyu11@163.com
Project-URL: Bug Reports, https://github.com/TheY11/Castl/issues
Project-URL: Source, https://github.com/TheY11/Castl
Keywords: consensus,spatially variable genes,spatial transcriptomics
Classifier: Programming Language :: Python :: 3
Classifier: License :: OSI Approved :: MIT License
Classifier: Operating System :: OS Independent
Classifier: Intended Audience :: Science/Research
Classifier: Topic :: Scientific/Engineering :: Bio-Informatics
Requires-Python: >=3.8
License-File: LICENSE
Requires-Dist: numpy >=1.21.0
Requires-Dist: pandas >=1.3.0
Requires-Dist: rpy2 >=3.5.0
Requires-Dist: scipy >=1.7.0
Requires-Dist: statsmodels >=0.13.0
Requires-Dist: anndata >=0.8.0
Requires-Dist: scanpy >=1.9.0
Requires-Dist: scikit-learn >=1.0.0
Requires-Dist: matplotlib >=3.5.0
Requires-Dist: seaborn >=0.12.0
Provides-Extra: dev
Requires-Dist: pytest >=6.0 ; extra == 'dev'
Requires-Dist: black >=21.0 ; extra == 'dev'
Requires-Dist: flake8 >=3.9 ; extra == 'dev'
Requires-Dist: mypy >=0.900 ; extra == 'dev'
Requires-Dist: sphinx >=4.0 ; extra == 'dev'
Provides-Extra: test
Requires-Dist: pytest >=6.0 ; extra == 'test'
Requires-Dist: pytest-cov >=2.0 ; extra == 'test'
